LICENSE
README.md
pyproject.toml
setup.cfg
setup.py
lyncs_utils/__init__.py
lyncs_utils/class_utils.py
lyncs_utils/contextlib.py
lyncs_utils/extensions.py
lyncs_utils/functools.py
lyncs_utils/io.py
lyncs_utils/itertools.py
lyncs_utils/logical.py
lyncs_utils/math.py
lyncs_utils/numpy.py
lyncs_utils/pytest.py
lyncs_utils.egg-info/PKG-INFO
lyncs_utils.egg-info/SOURCES.txt
lyncs_utils.egg-info/dependency_links.txt
lyncs_utils.egg-info/entry_points.txt
lyncs_utils.egg-info/requires.txt
lyncs_utils.egg-info/top_level.txt
test/test_class_utils.py
test/test_contextlib.py
test/test_extensions.py
test/test_functools.py
test/test_io.py
test/test_itertools.py
test/test_logical.py
test/test_math.py
test/test_numpy.py
test/test_pytest.py