Metadata-Version: 2.1
Name: lyncs_utils
Version: 0.5.1
Summary: Collection of generic-purpose and stand-alone functions
Home-page: https://github.com/Lyncs-API/lyncs.utils
Author: Simone Bacchio
Author-email: s.bacchio@gmail.com
Project-URL: Source, https://github.com/Lyncs-API/lyncs.utils
Project-URL: Documentation, https://github.com/Lyncs-API/lyncs.utils/README.md
Project-URL: Tracker, https://github.com/Lyncs-API/lyncs.utils/issues
Project-URL: Download, https://github.com/Lyncs-API/lyncs.utils/archive/master.zip
Keywords: Collection,generic-purpose,stand-alone,functions
Classifier: Operating System :: Unix
Classifier: Programming Language :: Python :: 3 :: Only
Classifier: Development Status :: 1 - Planning
Classifier: Topic :: Scientific/Engineering :: Physics
Classifier: Intended Audience :: Education
Classifier: Natural Language :: English
Classifier: License :: OSI Approved :: BSD License
Classifier: Intended Audience :: Developers
Classifier: Intended Audience :: Science/Research
License-File: LICENSE
Requires-Dist: dataclasses
Requires-Dist: lyncs-setuptools
Provides-Extra: numpy
Requires-Dist: numpy; extra == "numpy"
Provides-Extra: clickit
Requires-Dist: click; extra == "clickit"
Provides-Extra: test
Requires-Dist: pytest; extra == "test"
Requires-Dist: pytest-cov; extra == "test"
Requires-Dist: ipython; extra == "test"
Requires-Dist: numpy; extra == "test"
Requires-Dist: lyncs_setuptools; extra == "test"
Provides-Extra: all
Requires-Dist: ipython; extra == "all"
Requires-Dist: pytest; extra == "all"
Requires-Dist: click; extra == "all"
Requires-Dist: pytest-cov; extra == "all"
Requires-Dist: lyncs_setuptools; extra == "all"
Requires-Dist: numpy; extra == "all"
